rizaio/__init__.py
rizaio/_base_client.py
rizaio/_client.py
rizaio/_compat.py
rizaio/_constants.py
rizaio/_exceptions.py
rizaio/_files.py
rizaio/_models.py
rizaio/_qs.py
rizaio/_resource.py
rizaio/_response.py
rizaio/_streaming.py
rizaio/_types.py
rizaio/_version.py
rizaio/pagination.py
rizaio/py.typed
rizaio/_utils/__init__.py
rizaio/_utils/_logs.py
rizaio/_utils/_proxy.py
rizaio/_utils/_reflection.py
rizaio/_utils/_resources_proxy.py
rizaio/_utils/_streams.py
rizaio/_utils/_sync.py
rizaio/_utils/_transform.py
rizaio/_utils/_typing.py
rizaio/_utils/_utils.py
rizaio/lib/.keep
rizaio/resources/__init__.py
rizaio/resources/command.py
rizaio/resources/executions.py
rizaio/resources/secrets.py
rizaio/resources/tools.py
rizaio/resources/runtimes/__init__.py
rizaio/resources/runtimes/revisions.py
rizaio/resources/runtimes/runtimes.py
rizaio/types/__init__.py
rizaio/types/command_exec_func_params.py
rizaio/types/command_exec_func_response.py
rizaio/types/command_exec_params.py
rizaio/types/command_exec_response.py
rizaio/types/execution.py
rizaio/types/execution_list_params.py
rizaio/types/runtime.py
rizaio/types/runtime_create_params.py
rizaio/types/runtime_delete_response.py
rizaio/types/runtime_list_params.py
rizaio/types/secret.py
rizaio/types/secret_create_params.py
rizaio/types/secret_list_params.py
rizaio/types/tool.py
rizaio/types/tool_create_params.py
rizaio/types/tool_exec_params.py
rizaio/types/tool_exec_response.py
rizaio/types/tool_list_params.py
rizaio/types/tool_update_params.py
rizaio/types/runtimes/__init__.py
rizaio/types/runtimes/revision.py
rizaio/types/runtimes/revision_create_params.py
rizaio/types/runtimes/revision_list_response.py
rizaio-0.12.0.dist-info/METADATA
rizaio-0.12.0.dist-info/WHEEL
rizaio-0.12.0.dist-info/licenses/LICENSE
rizaio-0.12.0.dist-info/RECORD
